odoo/addons/l10n_ro_account_period_close/README.rst
odoo/addons/l10n_ro_account_period_close/__init__.py
odoo/addons/l10n_ro_account_period_close/__manifest__.py
odoo/addons/l10n_ro_account_period_close/i18n/l10n_ro_account_period_close.pot
odoo/addons/l10n_ro_account_period_close/i18n/ro.po
odoo/addons/l10n_ro_account_period_close/models/__init__.py
odoo/addons/l10n_ro_account_period_close/models/account.py
odoo/addons/l10n_ro_account_period_close/models/account_period_close.py
odoo/addons/l10n_ro_account_period_close/readme/CONFIGURE.md
odoo/addons/l10n_ro_account_period_close/readme/CONTRIBUTORS.md
odoo/addons/l10n_ro_account_period_close/readme/DESCRIPTION.md
odoo/addons/l10n_ro_account_period_close/readme/INSTALL.md
odoo/addons/l10n_ro_account_period_close/readme/USAGE.md
odoo/addons/l10n_ro_account_period_close/security/account_security.xml
odoo/addons/l10n_ro_account_period_close/security/ir.model.access.csv
odoo/addons/l10n_ro_account_period_close/static/description/icon.png
odoo/addons/l10n_ro_account_period_close/static/description/index.html
odoo/addons/l10n_ro_account_period_close/tests/__init__.py
odoo/addons/l10n_ro_account_period_close/tests/test_period_closing.py
odoo/addons/l10n_ro_account_period_close/views/account_period_close_view.xml
odoo/addons/l10n_ro_account_period_close/wizards/__init__.py
odoo/addons/l10n_ro_account_period_close/wizards/wizard_account_period_closing.py
odoo/addons/l10n_ro_account_period_close/wizards/wizard_account_period_closing_view.xml
odoo_addon_l10n_ro_account_period_close-19.0.1.1.0.dist-info/METADATA
odoo_addon_l10n_ro_account_period_close-19.0.1.1.0.dist-info/WHEEL
odoo_addon_l10n_ro_account_period_close-19.0.1.1.0.dist-info/top_level.txt
odoo_addon_l10n_ro_account_period_close-19.0.1.1.0.dist-info/RECORD
